hanuman/__init__.py
hanuman/main.py
hanuman-0.1.6.dist-info/LICENSE
hanuman-0.1.6.dist-info/METADATA
hanuman-0.1.6.dist-info/WHEEL
hanuman-0.1.6.dist-info/entry_points.txt
hanuman-0.1.6.dist-info/top_level.txt
hanuman-0.1.6.dist-info/RECORD
